README.md
setup.cfg
setup.py
ImageExtractor/Download.py
ImageExtractor/Extractor.py
ImageExtractor/Helper.py
ImageExtractor/Logger.py
ImageExtractor/Scheduler.py
ImageExtractor/Scrapper.py
ImageExtractor/__init__.py
ImageExtractor.egg-info/PKG-INFO
ImageExtractor.egg-info/SOURCES.txt
ImageExtractor.egg-info/dependency_links.txt
ImageExtractor.egg-info/requires.txt
ImageExtractor.egg-info/top_level.txt
ImageExtractor/config/log_config.py
ImageExtractor/config/scheduler_config.py