Metadata-Version: 2.1
Name: ImageExtractor
Version: 1.2
Summary: ImageExtractor library is useful to help the user download any kind of Images at any date and time over the internet. These images will get downloaded as a job and then let user know that the images have been downloaded.
Home-page: https://github.com/Sparab16/Extractor
Author: Shreyas Parab
Author-email: shreyas.parab16@gmail.com
License: UNKNOWN
Download-URL: https://github.com/Sparab16/Extractor/archive/refs/tags/v1.1.tar.gz
Keywords: Python,Selenium,Flask,Scheduling,Extract,Image Extract
Platform: UNKNOWN
Classifier: Programming Language :: Python :: 3.6
Classifier: License :: OSI Approved :: MIT License
Classifier: Development Status :: 5 - Production/Stable
Classifier: Intended Audience :: Developers
Classifier: Topic :: Software Development :: Build Tools
Requires-Python: >=3.6
